setup.cfg
setup.py
pyramid_lawn/__init__.py
pyramid_lawn.egg-info/PKG-INFO
pyramid_lawn.egg-info/SOURCES.txt
pyramid_lawn.egg-info/dependency_links.txt
pyramid_lawn.egg-info/entry_points.txt
pyramid_lawn.egg-info/not-zip-safe
pyramid_lawn.egg-info/requires.txt
pyramid_lawn.egg-info/top_level.txt