Metadata-Version: 1.1
Name: pyramid-lawn
Version: 1.0
Summary: Tell the kids to get off your lawn.
Home-page: UNKNOWN
Author: Chris Rossi
Author-email: chris@archimedeanco.com
License: BSD-derived (http://www.repoze.org/LICENSE.txt)
Keywords: wsgi pylons web pyramid
Platform: UNKNOWN
Classifier: Intended Audience :: Developers
Classifier: Programming Language :: Python
Classifier: Framework :: Pyramid
Classifier: License :: Repoze Public License
Classifier: Programming Language :: Python :: 2.6
Classifier: Programming Language :: Python :: 2.7
Classifier: Programming Language :: Python :: 3.2
Classifier: Programming Language :: Python :: 3.3
Classifier: Programming Language :: Python :: Implementation :: CPython
Classifier: Programming Language :: Python :: Implementation :: PyPy
